fixpoint/__init__.py
fixpoint/client/__init__.py
fixpoint/client/_async/__init__.py
fixpoint/client/_async/_config.py
fixpoint/client/_async/agents.py
fixpoint/client/_async/client.py
fixpoint/client/_async/data.py
fixpoint/client/_async/documents.py
fixpoint/client/_async/extractions.py
fixpoint/client/_async/human.py
fixpoint/client/_async/parsing.py
fixpoint/client/_async/research.py
fixpoint/client/_async/sitemaps.py
fixpoint/client/_async/workflows.py
fixpoint/client/_common/__init__.py
fixpoint/client/_common/core.py
fixpoint/client/_common/data.py
fixpoint/client/_common/documents.py
fixpoint/client/_common/extraction.py
fixpoint/client/_common/human.py
fixpoint/client/_common/parsing.py
fixpoint/client/_common/research.py
fixpoint/client/_common/sitemaps.py
fixpoint/client/_common/webresearcher.py
fixpoint/client/_sync/__init__.py
fixpoint/client/_sync/_config.py
fixpoint/client/_sync/agents.py
fixpoint/client/_sync/client.py
fixpoint/client/_sync/data.py
fixpoint/client/_sync/documents.py
fixpoint/client/_sync/extractions.py
fixpoint/client/_sync/human.py
fixpoint/client/_sync/parsing.py
fixpoint/client/_sync/research.py
fixpoint/client/_sync/sitemaps.py
fixpoint/client/docs/__init__.py
fixpoint/client/docs/_tabular.py
fixpoint/client/types.py
fixpoint/errors.py
fixpoint/py.typed
fixpoint/types.py
fixpoint/utils/__init__.py
fixpoint/utils/concurrency.py
fixpoint/utils/retry.py
fixpoint/workflows/__init__.py
fixpoint/workflows/structured/__init__.py
fixpoint-0.28.0.dist-info/LICENSE
fixpoint-0.28.0.dist-info/METADATA
fixpoint-0.28.0.dist-info/WHEEL
fixpoint-0.28.0.dist-info/RECORD
