Metadata-Version: 2.3
Name: fixpoint
Version: 0.28.0
Summary: Fixpoint client - an AI that can research the web
License: License :: OSI Approved :: Apache Software License
Author: Fixpoint
Author-email: team@fixpoint.co
Requires-Python: >=3.10,<4.0
Classifier: License :: OSI Approved :: Apache Software License
Classifier: License :: Other/Proprietary License
Classifier: Programming Language :: Python :: 3
Classifier: Programming Language :: Python :: 3.10
Classifier: Programming Language :: Python :: 3.11
Classifier: Programming Language :: Python :: 3.12
Classifier: Programming Language :: Python :: 3.13
Requires-Dist: fixpoint-common (>=0.28.0,<0.29.0)
Requires-Dist: httpx (>=0.27.2,<0.28.0)
Requires-Dist: pydantic (>=2)
Requires-Dist: typing-extensions (>=4.7.1)
Project-URL: Homepage, https://fixpoint.co/
Project-URL: Repository, https://github.com/gofixpoint/fixpoint
